normalizer/__init__.py
normalizer/abbreviation.py
normalizer/currency.py
normalizer/date_norm.py
normalizer/num2str.py
normalizer/num_norm.py
normalizer/punctuation.py
normalizer/rule_registry.py
phonemizer/__init__.py
phonemizer/ug_phonemizer.py
tokenizer/__init__.py
tokenizer/base_tokenizer.py
tokenizer/bpe_tokenizer.py
tokenizer/char_tokenizer.py
tokenizer/sentencepiece_tokenizer.py
tokenizer/tokenizer_factory.py
tokenizer/word_tokenizer.py
tokenizer/wordpiece_tokenizer.py
ugtext_processer-0.1.4.dist-info/METADATA
ugtext_processer-0.1.4.dist-info/WHEEL
ugtext_processer-0.1.4.dist-info/top_level.txt
ugtext_processer-0.1.4.dist-info/RECORD
