Metadata-Version: 2.4
Name: ugtext_processer
Version: 0.1.4
Summary: text processing for uyghur script
Author-email: uyplayer <uyplayer@outlook.com>
Classifier: Programming Language :: Python :: 3.9
Classifier: Operating System :: OS Independent
Requires-Python: >=3.9
Requires-Dist: pytest
Requires-Dist: epitran
Requires-Dist: sentencepiece
Requires-Dist: tokenizers
Provides-Extra: test
Requires-Dist: pytest; extra == "test"
